eynollah/Charis-Regular.ttf
eynollah/__init__.py
eynollah/extract_images.py
eynollah/eynollah.py
eynollah/eynollah_imports.py
eynollah/eynollah_ocr.py
eynollah/image_enhancer.py
eynollah/mb_ro_on_layout.py
eynollah/ocrd-tool.json
eynollah/ocrd_cli.py
eynollah/ocrd_cli_binarization.py
eynollah/patch_encoder.py
eynollah/plot.py
eynollah/processor.py
eynollah/sbb_binarize.py
eynollah/writer.py
eynollah/cli/__init__.py
eynollah/cli/cli.py
eynollah/cli/cli_binarize.py
eynollah/cli/cli_enhance.py
eynollah/cli/cli_extract_images.py
eynollah/cli/cli_layout.py
eynollah/cli/cli_models.py
eynollah/cli/cli_ocr.py
eynollah/cli/cli_readingorder.py
eynollah/model_zoo/__init__.py
eynollah/model_zoo/default_specs.py
eynollah/model_zoo/model_zoo.py
eynollah/model_zoo/specs.py
eynollah/model_zoo/types.py
eynollah/training/__init__.py
eynollah/training/build_model_load_pretrained_weights_and_save.py
eynollah/training/cli.py
eynollah/training/extract_line_gt.py
eynollah/training/generate_gt_for_training.py
eynollah/training/gt_gen_utils.py
eynollah/training/inference.py
eynollah/training/metrics.py
eynollah/training/models.py
eynollah/training/train.py
eynollah/training/utils.py
eynollah/training/weights_ensembling.py
eynollah/utils/__init__.py
eynollah/utils/contour.py
eynollah/utils/counter.py
eynollah/utils/drop_capitals.py
eynollah/utils/font.py
eynollah/utils/is_nan.py
eynollah/utils/marginals.py
eynollah/utils/pil_cv2.py
eynollah/utils/resize.py
eynollah/utils/rotate.py
eynollah/utils/separate_lines.py
eynollah/utils/shm.py
eynollah/utils/utils_ocr.py
eynollah/utils/xml.py
eynollah-0.7.0.dist-info/licenses/LICENSE
eynollah-0.7.0.dist-info/METADATA
eynollah-0.7.0.dist-info/WHEEL
eynollah-0.7.0.dist-info/entry_points.txt
eynollah-0.7.0.dist-info/top_level.txt
eynollah-0.7.0.dist-info/RECORD
