Metadata-Version: 2.4
Name: eynollah
Version: 0.7.0
Summary: Document Layout Analysis
Author: Vahid Rezanezhad, Staatsbibliothek zu Berlin - Preußischer Kulturbesitz
License:                                  Apache License
Project-URL: Homepage, https://github.com/qurator-spk/eynollah
Project-URL: Repository, https://github.com/qurator-spk/eynollah.git
Keywords: document layout analysis,image segmentation,binarization,optical character recognition
Classifier: Development Status :: 4 - Beta
Classifier: Environment :: Console
Classifier: Intended Audience :: Science/Research
Classifier: License :: OSI Approved :: Apache Software License
Classifier: Programming Language :: Python :: 3
Classifier: Programming Language :: Python :: 3.8
Classifier: Programming Language :: Python :: 3.9
Classifier: Programming Language :: Python :: 3.10
Classifier: Programming Language :: Python :: 3.11
Classifier: Programming Language :: Python :: 3 :: Only
Classifier: Topic :: Scientific/Engineering :: Image Processing
Requires-Python: >=3.8
License-File: LICENSE
Requires-Dist: ocrd>=3.3.0
Requires-Dist: numpy<1.24.0
Requires-Dist: scikit-learn>=0.23.2
Requires-Dist: tensorflow<2.13
Requires-Dist: numba<=0.58.1
Requires-Dist: scikit-image
Requires-Dist: biopython
Requires-Dist: tabulate
Provides-Extra: test
Requires-Dist: pytest; extra == "test"
Requires-Dist: pytest-isolate; extra == "test"
Requires-Dist: coverage[toml]; extra == "test"
Requires-Dist: black; extra == "test"
Provides-Extra: ocr
Requires-Dist: torch; extra == "ocr"
Requires-Dist: transformers<=4.30.2; extra == "ocr"
Provides-Extra: plotting
Requires-Dist: matplotlib; extra == "plotting"
Provides-Extra: training
Requires-Dist: sacred; extra == "training"
Requires-Dist: seaborn; extra == "training"
Requires-Dist: numpy<1.24.0; extra == "training"
Requires-Dist: tqdm; extra == "training"
Requires-Dist: imutils; extra == "training"
Requires-Dist: scipy; extra == "training"
Dynamic: license-file
